critsapi/__init__.py
critsapi/critsapi.py
critsapi/critsdbapi.py
critsapi/exceptions.py
critsapi/vocabulary.py
critsapi-0.1.1.dist-info/METADATA
critsapi-0.1.1.dist-info/RECORD
critsapi-0.1.1.dist-info/WHEEL
critsapi-0.1.1.dist-info/top_level.txt
